CHANGELOG.md
LICENSE
MANIFEST.in
README.md
ROADMAP.md
setup.py
bowl/__init__.py
bowl/__init__.pyc
bowl/api.py
bowl/api.pyc
bowl/cli.py
bowl/cli.pyc
bowl.egg-info/PKG-INFO
bowl.egg-info/SOURCES.txt
bowl.egg-info/dependency_links.txt
bowl.egg-info/entry_points.txt
bowl.egg-info/requires.txt
bowl.egg-info/top_level.txt
bowl/cli_opts/__init__.py
bowl/cli_opts/__init__.pyc
bowl/cli_opts/add.py
bowl/cli_opts/add.pyc
bowl/cli_opts/connect.py
bowl/cli_opts/connect.pyc
bowl/cli_opts/delete.py
bowl/cli_opts/delete.pyc
bowl/cli_opts/disconnect.py
bowl/cli_opts/disconnect.pyc
bowl/cli_opts/hosts.py
bowl/cli_opts/hosts.pyc
bowl/cli_opts/image_import.py
bowl/cli_opts/image_import.pyc
bowl/cli_opts/images.py
bowl/cli_opts/images.pyc
bowl/cli_opts/info.py
bowl/cli_opts/info.pyc
bowl/cli_opts/kill.py
bowl/cli_opts/kill.pyc
bowl/cli_opts/link.py
bowl/cli_opts/link.pyc
bowl/cli_opts/list.py
bowl/cli_opts/list.pyc
bowl/cli_opts/login.py
bowl/cli_opts/login.pyc
bowl/cli_opts/logout.py
bowl/cli_opts/logout.pyc
bowl/cli_opts/logs.py
bowl/cli_opts/logs.pyc
bowl/cli_opts/new.py
bowl/cli_opts/new.pyc
bowl/cli_opts/remove.py
bowl/cli_opts/remove.pyc
bowl/cli_opts/repositories.py
bowl/cli_opts/repositories.pyc
bowl/cli_opts/services.py
bowl/cli_opts/services.pyc
bowl/cli_opts/snapshot.py
bowl/cli_opts/snapshot.pyc
bowl/cli_opts/snapshots.py
bowl/cli_opts/snapshots.pyc
bowl/cli_opts/start.py
bowl/cli_opts/start.pyc
bowl/cli_opts/stop.py
bowl/cli_opts/stop.pyc
bowl/cli_opts/subtract.py
bowl/cli_opts/subtract.pyc
bowl/cli_opts/test.py
bowl/cli_opts/test.pyc
bowl/cli_opts/unlink.py
bowl/cli_opts/unlink.pyc
bowl/cli_opts/update.py
bowl/cli_opts/update.pyc
bowl/cli_opts/version.py
bowl/cli_opts/version.pyc
bowl/containers/README.md
bowl/containers/.default/services/oses
bowl/containers/.default/services/debian/versions
bowl/containers/.default/services/debian/jessie/databases/databases
bowl/containers/.default/services/debian/jessie/databases/dockerfiles/rethinkdb/Dockerfile
bowl/containers/.default/services/debian/jessie/environment/environment
bowl/containers/.default/services/debian/jessie/services/services
