Metadata-Version: 1.0
Name: bowl
Version: 0.3.0
Summary: Tool for easily building and configuring virtual environments on top of Docker.
Home-page: UNKNOWN
Author: Charlie Lewis
Author-email: charlie.lewis42@gmail.com
License: LICENSE
Keywords: bowl,docker,virtual,environment,containers,services
Platform: UNKNOWN
